{"is_source_file": false, "format": "", "description": "", "external_files": [], "external_methods": [], "published": [], "classes": [], "methods": [], "calls": [], "search-terms": [], "state": 2, "file_id": 25, "knowledge_revision": 64, "git_revision": "2e190c28ed698a26bbaca8c5e6ffd822769bb3a2", "hash": "57b37bba8009db446317dfe168f8ceda", "format-version": 4, "code-base-name": "express_backend", "filename": "express_backend/DEVELOPER_CHECKLIST.md", "revision_history": [{"64": "2e190c28ed698a26bbaca8c5e6ffd822769bb3a2"}]}